README.txt
setup.py
docs/HISTORY.txt
docs/INSTALL.txt
docs/LICENSE.GPL
docs/LICENSE.txt
openc/__init__.py
openc.objectsfromlinks.egg-info/PKG-INFO
openc.objectsfromlinks.egg-info/SOURCES.txt
openc.objectsfromlinks.egg-info/dependency_links.txt
openc.objectsfromlinks.egg-info/entry_points.txt
openc.objectsfromlinks.egg-info/namespace_packages.txt
openc.objectsfromlinks.egg-info/not-zip-safe
openc.objectsfromlinks.egg-info/requires.txt
openc.objectsfromlinks.egg-info/top_level.txt
openc/objectsfromlinks/README.txt
openc/objectsfromlinks/__init__.py
openc/objectsfromlinks/adapters.py
openc/objectsfromlinks/configure.zcml
openc/objectsfromlinks/html_to_embed.py
openc/objectsfromlinks/interfaces.py
openc/objectsfromlinks/tests.py
openc/objectsfromlinks/Extensions/Install.py